README.md
setup.cfg
setup.py
openlr/__init__.py
openlr/__main__.py
openlr/_version.py
openlr/binary_format.py
openlr/locations.py
openlr/openlr_bytes_io.py
openlr/utils.py
openlr/xml_format.py
openlr.egg-info/PKG-INFO
openlr.egg-info/SOURCES.txt
openlr.egg-info/dependency_links.txt
openlr.egg-info/top_level.txt